{
  "Lasers": [
    {
      "Laservector": "0,-5",
      "Angle": -90.0,
      "Speed": 0,
      "Fromplayer": true,
      "Big": false,
      "IsHit": false,
      "Ammosize": 5,
      "Counter": 143,
      "Hitbox": "153,22,5,5",
      "Position": "155,24"
    },
    {
      "Laservector": "0,-5",
      "Angle": -90.0,
      "Speed": 0,
      "Fromplayer": true,
      "Big": false,
      "IsHit": false,
      "Ammosize": 5,
      "Counter": 115,
      "Hitbox": "183,162,5,5",
      "Position": "185,164"
    },
    {
      "Laservector": "1,5",
      "Angle": 78.69006752597979,
      "Speed": 0,
      "Fromplayer": false,
      "Big": false,
      "IsHit": false,
      "Ammosize": 5,
      "Counter": 106,
      "Hitbox": "159,726,5,5",
      "Position": "161,728"
    },
    {
      "Laservector": "0,-5",
      "Angle": -90.0,
      "Speed": 0,
      "Fromplayer": true,
      "Big": false,
      "IsHit": false,
      "Ammosize": 5,
      "Counter": 84,
      "Hitbox": "183,317,5,5",
      "Position": "185,319"
    },
    {
      "Laservector": "0,-5",
      "Angle": -90.0,
      "Speed": 0,
      "Fromplayer": true,
      "Big": false,
      "IsHit": false,
      "Ammosize": 5,
      "Counter": 55,
      "Hitbox": "193,462,5,5",
      "Position": "195,464"
    },
    {
      "Laservector": "1,5",
      "Angle": 78.69006752597979,
      "Speed": 0,
      "Fromplayer": false,
      "Big": false,
      "IsHit": false,
      "Ammosize": 5,
      "Counter": 47,
      "Hitbox": "100,431,5,5",
      "Position": "102,433"
    },
    {
      "Laservector": "-1,5",
      "Angle": 101.30993247402021,
      "Speed": 0,
      "Fromplayer": false,
      "Big": false,
      "IsHit": false,
      "Ammosize": 5,
      "Counter": 47,
      "Hitbox": "6,431,5,5",
      "Position": "8,433"
    },
    {
      "Laservector": "0,5",
      "Angle": 90.0,
      "Speed": 0,
      "Fromplayer": false,
      "Big": false,
      "IsHit": false,
      "Ammosize": 5,
      "Counter": 47,
      "Hitbox": "462,306,5,5",
      "Position": "464,308"
    },
    {
      "Laservector": "0,-5",
      "Angle": -90.0,
      "Speed": 0,
      "Fromplayer": true,
      "Big": false,
      "IsHit": false,
      "Ammosize": 5,
      "Counter": 25,
      "Hitbox": "203,612,5,5",
      "Position": "205,614"
    }
  ],
  "Asteroids": [
    {
      "Speed": 5,
      "IsHit": false,
      "Position": "115,810",
      "Hitbox": "90,790,50,40"
    }
  ],
  "EnemyShips": [
    {
      "Position": "102,175",
      "Name": 1,
      "IsHit": false,
      "IsDead": false,
      "IsMoving": false,
      "Hitbox": "77,155,50,40"
    },
    {
      "Position": "486,175",
      "Name": 0,
      "IsHit": false,
      "IsDead": false,
      "IsMoving": false,
      "Hitbox": "461,155,50,40"
    }
  ],
  "Powerups": [],
  "Player": {
    "left": false,
    "Position": "305,764",
    "Weapon": 3,
    "IsDead": false,
    "IsMoving": false,
    "Hitbox": "290,752,30,25",
    "Health": 200
  },
  "Boss": null,
  "Score": 440,
  "HighScore": 6290,
  "PlayerName": "Kuki",
  "Asteroidspeed": 5,
  "Firerate": 30,
  "Poweruprate": 40,
  "Enemyshottimechange": 60,
  "Bossshottimechange": 40,
  "EnemySpawnCount": 2,
  "BossHealth": 400,
  "Godmode": false,
  "Difficultyness": 1,
  "RapidfireTime": 0,
  "StrongTime": 0,
  "WeaponTime": 0,
  "Shield": true,
  "Rapid": false,
  "Strong": false,
  "Weaponon": false,
  "Area": "550,864.0000000000001"
}